odoo/addons/account_invoice_start_end_dates/README.rst
odoo/addons/account_invoice_start_end_dates/__init__.py
odoo/addons/account_invoice_start_end_dates/__manifest__.py
odoo/addons/account_invoice_start_end_dates/demo/product_demo.xml
odoo/addons/account_invoice_start_end_dates/i18n/account_invoice_start_end_dates.pot
odoo/addons/account_invoice_start_end_dates/i18n/fr.po
odoo/addons/account_invoice_start_end_dates/i18n/hr.po
odoo/addons/account_invoice_start_end_dates/i18n/hr_HR.po
odoo/addons/account_invoice_start_end_dates/i18n/it.po
odoo/addons/account_invoice_start_end_dates/i18n/nl_NL.po
odoo/addons/account_invoice_start_end_dates/i18n/pt.po
odoo/addons/account_invoice_start_end_dates/models/__init__.py
odoo/addons/account_invoice_start_end_dates/models/account_invoice.py
odoo/addons/account_invoice_start_end_dates/models/account_move_line.py
odoo/addons/account_invoice_start_end_dates/models/product.py
odoo/addons/account_invoice_start_end_dates/static/description/icon.png
odoo/addons/account_invoice_start_end_dates/tests/__init__.py
odoo/addons/account_invoice_start_end_dates/tests/test_invoice_start_end_dates.py
odoo/addons/account_invoice_start_end_dates/views/account_invoice.xml
odoo/addons/account_invoice_start_end_dates/views/account_move.xml
odoo/addons/account_invoice_start_end_dates/views/product.xml
odoo11_addon_account_invoice_start_end_dates-11.0.1.0.0.99.dev9.dist-info/METADATA
odoo11_addon_account_invoice_start_end_dates-11.0.1.0.0.99.dev9.dist-info/WHEEL
odoo11_addon_account_invoice_start_end_dates-11.0.1.0.0.99.dev9.dist-info/top_level.txt
odoo11_addon_account_invoice_start_end_dates-11.0.1.0.0.99.dev9.dist-info/RECORD
